{"nodes": [{"id": "users_ayberkkarataban_ssfl_with_psuedo_labeling_src_ssfl_comm_py", "label": "comm.py", "file_type": "code", "source_file": "src/ssfl/comm.py", "source_location": "L1"}, {"id": "users_ayberkkarataban_ssfl_with_psuedo_labeling_src_ssfl_comm_scenario_num_clients", "label": "scenario_num_clients()", "file_type": "code", "source_file": "src/ssfl/comm.py", "source_location": "L65", "_callable": true}, {"id": "users_ayberkkarataban_ssfl_with_psuedo_labeling_src_ssfl_comm_model_param_count", "label": "model_param_count()", "file_type": "code", "source_file": "src/ssfl/comm.py", "source_location": "L76", "_callable": true}, {"id": "users_ayberkkarataban_ssfl_with_psuedo_labeling_src_ssfl_comm_roundcost", "label": "RoundCost", "file_type": "code", "source_file": "src/ssfl/comm.py", "source_location": "L89", "_callable": true}, {"id": "users_ayberkkarataban_ssfl_with_psuedo_labeling_src_ssfl_comm_roundcost_upload_bytes", "label": ".upload_bytes()", "file_type": "code", "source_file": "src/ssfl/comm.py", "source_location": "L99", "_callable": true}, {"id": "users_ayberkkarataban_ssfl_with_psuedo_labeling_src_ssfl_comm_roundcost_download_bytes", "label": ".download_bytes()", "file_type": "code", "source_file": "src/ssfl/comm.py", "source_location": "L104", "_callable": true}, {"id": "users_ayberkkarataban_ssfl_with_psuedo_labeling_src_ssfl_comm_roundcost_total_bytes", "label": ".total_bytes()", "file_type": "code", "source_file": "src/ssfl/comm.py", "source_location": "L109", "_callable": true}, {"id": "users_ayberkkarataban_ssfl_with_psuedo_labeling_src_ssfl_comm_roundcost_total_mb", "label": ".total_mb()", "file_type": "code", "source_file": "src/ssfl/comm.py", "source_location": "L113", "_callable": true}, {"id": "users_ayberkkarataban_ssfl_with_psuedo_labeling_src_ssfl_comm_round_cost", "label": "round_cost()", "file_type": "code", "source_file": "src/ssfl/comm.py", "source_location": "L117", "_callable": true}, {"id": "users_ayberkkarataban_ssfl_with_psuedo_labeling_src_ssfl_comm_round_cost_for_config", "label": "round_cost_for_config()", "file_type": "code", "source_file": "src/ssfl/comm.py", "source_location": "L152", "_callable": true}, {"id": "runconfig", "label": "RunConfig", "file_type": "code", "source_file": "", "source_location": "", "origin_file": "/Users/ayberkkarataban/SSFL with Psuedo Labeling/src/ssfl/comm.py"}, {"id": "users_ayberkkarataban_ssfl_with_psuedo_labeling_src_ssfl_comm_open_set_cost_bytes", "label": "open_set_cost_bytes()", "file_type": "code", "source_file": "src/ssfl/comm.py", "source_location": "L179", "_callable": true}, {"id": "users_ayberkkarataban_ssfl_with_psuedo_labeling_src_ssfl_comm_cumulative_mb_curve", "label": "cumulative_mb_curve()", "file_type": "code", "source_file": "src/ssfl/comm.py", "source_location": "L198", "_callable": true}, {"id": "ndarray", "label": "ndarray", "file_type": "code", "source_file": "", "source_location": "", "origin_file": "/Users/ayberkkarataban/SSFL with Psuedo Labeling/src/ssfl/comm.py"}, {"id": "users_ayberkkarataban_ssfl_with_psuedo_labeling_src_ssfl_comm_costat", "label": "CostAt", "file_type": "code", "source_file": "src/ssfl/comm.py", "source_location": "L208", "_callable": true}, {"id": "users_ayberkkarataban_ssfl_with_psuedo_labeling_src_ssfl_comm_cost_at_accuracy", "label": "cost_at_accuracy()", "file_type": "code", "source_file": "src/ssfl/comm.py", "source_location": "L222", "_callable": true}, {"id": "any", "label": "Any", "file_type": "code", "source_file": "", "source_location": "", "origin_file": "/Users/ayberkkarataban/SSFL with Psuedo Labeling/src/ssfl/comm.py"}, {"id": "users_ayberkkarataban_ssfl_with_psuedo_labeling_src_ssfl_comm_cost_at_top_acc", "label": "cost_at_top_acc()", "file_type": "code", "source_file": "src/ssfl/comm.py", "source_location": "L248", "_callable": true}, {"id": "users_ayberkkarataban_ssfl_with_psuedo_labeling_src_ssfl_comm_cost_at_targets", "label": "cost_at_targets()", "file_type": "code", "source_file": "src/ssfl/comm.py", "source_location": "L258", "_callable": true}, {"id": "users_ayberkkarataban_ssfl_with_psuedo_labeling_src_ssfl_comm_run_comm_summary", "label": "run_comm_summary()", "file_type": "code", "source_file": "src/ssfl/comm.py", "source_location": "L275", "_callable": true}, {"id": "path", "label": "Path", "file_type": "code", "source_file": "", "source_location": "", "origin_file": "/Users/ayberkkarataban/SSFL with Psuedo Labeling/src/ssfl/comm.py"}, {"id": "users_ayberkkarataban_ssfl_with_psuedo_labeling_src_ssfl_comm_rationale_1", "label": "Analytic communication-cost accounting (PRD F6; Table IV, Fig. 6).  Every byte c", "file_type": "rationale", "source_file": "src/ssfl/comm.py", "source_location": "L1"}, {"id": "users_ayberkkarataban_ssfl_with_psuedo_labeling_src_ssfl_comm_rationale_66", "label": "Client count for a partition scenario (1 -> 27, 2 -> 89, 3 -> 89).", "file_type": "rationale", "source_file": "src/ssfl/comm.py", "source_location": "L66"}, {"id": "users_ayberkkarataban_ssfl_with_psuedo_labeling_src_ssfl_comm_rationale_77", "label": "Parameter count of a classifier by model name (e.g. cnn -> 248,395).      Lazily", "file_type": "rationale", "source_file": "src/ssfl/comm.py", "source_location": "L77"}, {"id": "users_ayberkkarataban_ssfl_with_psuedo_labeling_src_ssfl_comm_rationale_90", "label": "Analytic communication cost of one round of one method.", "file_type": "rationale", "source_file": "src/ssfl/comm.py", "source_location": "L90"}, {"id": "users_ayberkkarataban_ssfl_with_psuedo_labeling_src_ssfl_comm_rationale_100", "label": "Client -> server bytes per round across all clients.", "file_type": "rationale", "source_file": "src/ssfl/comm.py", "source_location": "L100"}, {"id": "users_ayberkkarataban_ssfl_with_psuedo_labeling_src_ssfl_comm_rationale_105", "label": "Server -> client bytes per round across all clients.", "file_type": "rationale", "source_file": "src/ssfl/comm.py", "source_location": "L105"}, {"id": "users_ayberkkarataban_ssfl_with_psuedo_labeling_src_ssfl_comm_rationale_126", "label": "Per-round cost of `method`, from the payload contract.      ``param_count`` is r", "file_type": "rationale", "source_file": "src/ssfl/comm.py", "source_location": "L126"}, {"id": "users_ayberkkarataban_ssfl_with_psuedo_labeling_src_ssfl_comm_rationale_160", "label": "Per-round cost implied by a run's config (method, scenario, label mode).      ``", "file_type": "rationale", "source_file": "src/ssfl/comm.py", "source_location": "L160"}, {"id": "users_ayberkkarataban_ssfl_with_psuedo_labeling_src_ssfl_comm_rationale_186", "label": "One-time cost of distributing the open set D^o to every client (C@D^o).      App", "file_type": "rationale", "source_file": "src/ssfl/comm.py", "source_location": "L186"}, {"id": "users_ayberkkarataban_ssfl_with_psuedo_labeling_src_ssfl_comm_rationale_199", "label": "Cumulative MB after each of ``rounds`` rounds (shape ``[rounds]``).      Per-rou", "file_type": "rationale", "source_file": "src/ssfl/comm.py", "source_location": "L199"}, {"id": "users_ayberkkarataban_ssfl_with_psuedo_labeling_src_ssfl_comm_rationale_209", "label": "C@x result: cost at the first round an accuracy target is reached.      ``reache", "file_type": "rationale", "source_file": "src/ssfl/comm.py", "source_location": "L209"}, {"id": "users_ayberkkarataban_ssfl_with_psuedo_labeling_src_ssfl_comm_rationale_228", "label": "C@x: cumulative MB at the first round with ``test_acc >= target_acc``.      ``re", "file_type": "rationale", "source_file": "src/ssfl/comm.py", "source_location": "L228"}, {"id": "users_ayberkkarataban_ssfl_with_psuedo_labeling_src_ssfl_comm_rationale_251", "label": "C@Top-Acc: cost at the first round reaching the run's own best accuracy.", "file_type": "rationale", "source_file": "src/ssfl/comm.py", "source_location": "L251"}, {"id": "users_ayberkkarataban_ssfl_with_psuedo_labeling_src_ssfl_comm_rationale_264", "label": "The Table IV C@x bundle: ``{\"C@50\", \"C@75\", \"C@Top-Acc\"}`` by default.", "file_type": "rationale", "source_file": "src/ssfl/comm.py", "source_location": "L264"}, {"id": "users_ayberkkarataban_ssfl_with_psuedo_labeling_src_ssfl_comm_rationale_283", "label": "Communication summary for a completed run in ``results/<run-id>/``.      Reads t", "file_type": "rationale", "source_file": "src/ssfl/comm.py", "source_location": "L283"}], "edges": [{"source": "users_ayberkkarataban_ssfl_with_psuedo_labeling_src_ssfl_comm_py", "target": "json", "relation": "imports", "context": "import", "confidence": "EXTRACTED", "source_file": "src/ssfl/comm.py", "source_location": "L34", "weight": 1.0}, {"source": "users_ayberkkarataban_ssfl_with_psuedo_labeling_src_ssfl_comm_py", "target": "dataclasses", "relation": "imports_from", "context": "import", "confidence": "EXTRACTED", "source_file": "src/ssfl/comm.py", "source_location": "L35", "weight": 1.0}, {"source": "users_ayberkkarataban_ssfl_with_psuedo_labeling_src_ssfl_comm_py", "target": "pathlib", "relation": "imports_from", "context": "import", "confidence": "EXTRACTED", "source_file": "src/ssfl/comm.py", "source_location": "L36", "weight": 1.0}, {"source": "users_ayberkkarataban_ssfl_with_psuedo_labeling_src_ssfl_comm_py", "target": "typing", "relation": "imports_from", "context": "import", "confidence": "EXTRACTED", "source_file": "src/ssfl/comm.py", "source_location": "L37", "weight": 1.0}, {"source": "users_ayberkkarataban_ssfl_with_psuedo_labeling_src_ssfl_comm_py", "target": "numpy", "relation": "imports", "context": "import", "confidence": "EXTRACTED", "source_file": "src/ssfl/comm.py", "source_location": "L39", "weight": 1.0}, {"source": "users_ayberkkarataban_ssfl_with_psuedo_labeling_src_ssfl_comm_py", "target": "ssfl_config", "relation": "imports_from", "context": "import", "confidence": "EXTRACTED", "source_file": "src/ssfl/comm.py", "source_location": "L41", "weight": 1.0}, {"source": "users_ayberkkarataban_ssfl_with_psuedo_labeling_src_ssfl_comm_py", "target": "ssfl_methods_payloads", "relation": "imports_from", "context": "import", "confidence": "EXTRACTED", "source_file": "src/ssfl/comm.py", "source_location": "L42", "weight": 1.0}, {"source": "users_ayberkkarataban_ssfl_with_psuedo_labeling_src_ssfl_comm_py", "target": "ssfl_metrics", "relation": "imports_from", "context": "import", "confidence": "EXTRACTED", "source_file": "src/ssfl/comm.py", "source_location": "L43", "weight": 1.0}, {"source": "users_ayberkkarataban_ssfl_with_psuedo_labeling_src_ssfl_comm_py", "target": "users_ayberkkarataban_ssfl_with_psuedo_labeling_src_ssfl_comm_scenario_num_clients", "relation": "contains", "confidence": "EXTRACTED", "source_file": "src/ssfl/comm.py", "source_location": "L65", "weight": 1.0}, {"source": "users_ayberkkarataban_ssfl_with_psuedo_labeling_src_ssfl_comm_py", "target": "users_ayberkkarataban_ssfl_with_psuedo_labeling_src_ssfl_comm_model_param_count", "relation": "contains", "confidence": "EXTRACTED", "source_file": "src/ssfl/comm.py", "source_location": "L76", "weight": 1.0}, {"source": "users_ayberkkarataban_ssfl_with_psuedo_labeling_src_ssfl_comm_py", "target": "users_ayberkkarataban_ssfl_with_psuedo_labeling_src_ssfl_comm_roundcost", "relation": "contains", "confidence": "EXTRACTED", "source_file": "src/ssfl/comm.py", "source_location": "L89", "weight": 1.0}, {"source": "users_ayberkkarataban_ssfl_with_psuedo_labeling_src_ssfl_comm_roundcost", "target": "users_ayberkkarataban_ssfl_with_psuedo_labeling_src_ssfl_comm_roundcost_upload_bytes", "relation": "method", "confidence": "EXTRACTED", "source_file": "src/ssfl/comm.py", "source_location": "L99", "weight": 1.0}, {"source": "users_ayberkkarataban_ssfl_with_psuedo_labeling_src_ssfl_comm_roundcost", "target": "users_ayberkkarataban_ssfl_with_psuedo_labeling_src_ssfl_comm_roundcost_download_bytes", "relation": "method", "confidence": "EXTRACTED", "source_file": "src/ssfl/comm.py", "source_location": "L104", "weight": 1.0}, {"source": "users_ayberkkarataban_ssfl_with_psuedo_labeling_src_ssfl_comm_roundcost", "target": "users_ayberkkarataban_ssfl_with_psuedo_labeling_src_ssfl_comm_roundcost_total_bytes", "relation": "method", "confidence": "EXTRACTED", "source_file": "src/ssfl/comm.py", "source_location": "L109", "weight": 1.0}, {"source": "users_ayberkkarataban_ssfl_with_psuedo_labeling_src_ssfl_comm_roundcost", "target": "users_ayberkkarataban_ssfl_with_psuedo_labeling_src_ssfl_comm_roundcost_total_mb", "relation": "method", "confidence": "EXTRACTED", "source_file": "src/ssfl/comm.py", "source_location": "L113", "weight": 1.0}, {"source": "users_ayberkkarataban_ssfl_with_psuedo_labeling_src_ssfl_comm_py", "target": "users_ayberkkarataban_ssfl_with_psuedo_labeling_src_ssfl_comm_round_cost", "relation": "contains", "confidence": "EXTRACTED", "source_file": "src/ssfl/comm.py", "source_location": "L117", "weight": 1.0}, {"source": "users_ayberkkarataban_ssfl_with_psuedo_labeling_src_ssfl_comm_round_cost", "target": "users_ayberkkarataban_ssfl_with_psuedo_labeling_src_ssfl_comm_roundcost", "relation": "references", "context": "return_type", "confidence": "EXTRACTED", "source_file": "src/ssfl/comm.py", "source_location": "L117", "weight": 1.0}, {"source": "users_ayberkkarataban_ssfl_with_psuedo_labeling_src_ssfl_comm_py", "target": "users_ayberkkarataban_ssfl_with_psuedo_labeling_src_ssfl_comm_round_cost_for_config", "relation": "contains", "confidence": "EXTRACTED", "source_file": "src/ssfl/comm.py", "source_location": "L152", "weight": 1.0}, {"source": "users_ayberkkarataban_ssfl_with_psuedo_labeling_src_ssfl_comm_round_cost_for_config", "target": "runconfig", "relation": "references", "context": "parameter_type", "confidence": "EXTRACTED", "source_file": "src/ssfl/comm.py", "source_location": "L152", "weight": 1.0}, {"source": "users_ayberkkarataban_ssfl_with_psuedo_labeling_src_ssfl_comm_round_cost_for_config", "target": "users_ayberkkarataban_ssfl_with_psuedo_labeling_src_ssfl_comm_roundcost", "relation": "references", "context": "return_type", "confidence": "EXTRACTED", "source_file": "src/ssfl/comm.py", "source_location": "L152", "weight": 1.0}, {"source": "users_ayberkkarataban_ssfl_with_psuedo_labeling_src_ssfl_comm_py", "target": "users_ayberkkarataban_ssfl_with_psuedo_labeling_src_ssfl_comm_open_set_cost_bytes", "relation": "contains", "confidence": "EXTRACTED", "source_file": "src/ssfl/comm.py", "source_location": "L179", "weight": 1.0}, {"source": "users_ayberkkarataban_ssfl_with_psuedo_labeling_src_ssfl_comm_py", "target": "users_ayberkkarataban_ssfl_with_psuedo_labeling_src_ssfl_comm_cumulative_mb_curve", "relation": "contains", "confidence": "EXTRACTED", "source_file": "src/ssfl/comm.py", "source_location": "L198", "weight": 1.0}, {"source": "users_ayberkkarataban_ssfl_with_psuedo_labeling_src_ssfl_comm_cumulative_mb_curve", "target": "users_ayberkkarataban_ssfl_with_psuedo_labeling_src_ssfl_comm_roundcost", "relation": "references", "context": "parameter_type", "confidence": "EXTRACTED", "source_file": "src/ssfl/comm.py", "source_location": "L198", "weight": 1.0}, {"source": "users_ayberkkarataban_ssfl_with_psuedo_labeling_src_ssfl_comm_cumulative_mb_curve", "target": "ndarray", "relation": "references", "context": "return_type", "confidence": "EXTRACTED", "source_file": "src/ssfl/comm.py", "source_location": "L198", "weight": 1.0}, {"source": "users_ayberkkarataban_ssfl_with_psuedo_labeling_src_ssfl_comm_py", "target": "users_ayberkkarataban_ssfl_with_psuedo_labeling_src_ssfl_comm_costat", "relation": "contains", "confidence": "EXTRACTED", "source_file": "src/ssfl/comm.py", "source_location": "L208", "weight": 1.0}, {"source": "users_ayberkkarataban_ssfl_with_psuedo_labeling_src_ssfl_comm_py", "target": "users_ayberkkarataban_ssfl_with_psuedo_labeling_src_ssfl_comm_cost_at_accuracy", "relation": "contains", "confidence": "EXTRACTED", "source_file": "src/ssfl/comm.py", "source_location": "L222", "weight": 1.0}, {"source": "users_ayberkkarataban_ssfl_with_psuedo_labeling_src_ssfl_comm_cost_at_accuracy", "target": "any", "relation": "references", "context": "generic_arg", "confidence": "EXTRACTED", "source_file": "src/ssfl/comm.py", "source_location": "L222", "weight": 1.0}, {"source": "users_ayberkkarataban_ssfl_with_psuedo_labeling_src_ssfl_comm_cost_at_accuracy", "target": "users_ayberkkarataban_ssfl_with_psuedo_labeling_src_ssfl_comm_costat", "relation": "references", "context": "return_type", "confidence": "EXTRACTED", "source_file": "src/ssfl/comm.py", "source_location": "L222", "weight": 1.0}, {"source": "users_ayberkkarataban_ssfl_with_psuedo_labeling_src_ssfl_comm_py", "target": "users_ayberkkarataban_ssfl_with_psuedo_labeling_src_ssfl_comm_cost_at_top_acc", "relation": "contains", "confidence": "EXTRACTED", "source_file": "src/ssfl/comm.py", "source_location": "L248", "weight": 1.0}, {"source": "users_ayberkkarataban_ssfl_with_psuedo_labeling_src_ssfl_comm_cost_at_top_acc", "target": "any", "relation": "references", "context": "generic_arg", "confidence": "EXTRACTED", "source_file": "src/ssfl/comm.py", "source_location": "L248", "weight": 1.0}, {"source": "users_ayberkkarataban_ssfl_with_psuedo_labeling_src_ssfl_comm_cost_at_top_acc", "target": "users_ayberkkarataban_ssfl_with_psuedo_labeling_src_ssfl_comm_costat", "relation": "references", "context": "return_type", "confidence": "EXTRACTED", "source_file": "src/ssfl/comm.py", "source_location": "L248", "weight": 1.0}, {"source": "users_ayberkkarataban_ssfl_with_psuedo_labeling_src_ssfl_comm_py", "target": "users_ayberkkarataban_ssfl_with_psuedo_labeling_src_ssfl_comm_cost_at_targets", "relation": "contains", "confidence": "EXTRACTED", "source_file": "src/ssfl/comm.py", "source_location": "L258", "weight": 1.0}, {"source": "users_ayberkkarataban_ssfl_with_psuedo_labeling_src_ssfl_comm_cost_at_targets", "target": "any", "relation": "references", "context": "generic_arg", "confidence": "EXTRACTED", "source_file": "src/ssfl/comm.py", "source_location": "L258", "weight": 1.0}, {"source": "users_ayberkkarataban_ssfl_with_psuedo_labeling_src_ssfl_comm_cost_at_targets", "target": "users_ayberkkarataban_ssfl_with_psuedo_labeling_src_ssfl_comm_costat", "relation": "references", "context": "generic_arg", "confidence": "EXTRACTED", "source_file": "src/ssfl/comm.py", "source_location": "L258", "weight": 1.0}, {"source": "users_ayberkkarataban_ssfl_with_psuedo_labeling_src_ssfl_comm_py", "target": "users_ayberkkarataban_ssfl_with_psuedo_labeling_src_ssfl_comm_run_comm_summary", "relation": "contains", "confidence": "EXTRACTED", "source_file": "src/ssfl/comm.py", "source_location": "L275", "weight": 1.0}, {"source": "users_ayberkkarataban_ssfl_with_psuedo_labeling_src_ssfl_comm_run_comm_summary", "target": "path", "relation": "references", "context": "parameter_type", "confidence": "EXTRACTED", "source_file": "src/ssfl/comm.py", "source_location": "L275", "weight": 1.0}, {"source": "users_ayberkkarataban_ssfl_with_psuedo_labeling_src_ssfl_comm_run_comm_summary", "target": "any", "relation": "references", "context": "generic_arg", "confidence": "EXTRACTED", "source_file": "src/ssfl/comm.py", "source_location": "L275", "weight": 1.0}, {"source": "users_ayberkkarataban_ssfl_with_psuedo_labeling_src_ssfl_comm_round_cost", "target": "users_ayberkkarataban_ssfl_with_psuedo_labeling_src_ssfl_comm_roundcost", "relation": "calls", "context": "call", "confidence": "EXTRACTED", "source_file": "src/ssfl/comm.py", "source_location": "L139", "weight": 1.0}, {"source": "users_ayberkkarataban_ssfl_with_psuedo_labeling_src_ssfl_comm_round_cost_for_config", "target": "users_ayberkkarataban_ssfl_with_psuedo_labeling_src_ssfl_comm_scenario_num_clients", "relation": "calls", "context": "call", "confidence": "EXTRACTED", "source_file": "src/ssfl/comm.py", "source_location": "L166", "weight": 1.0}, {"source": "users_ayberkkarataban_ssfl_with_psuedo_labeling_src_ssfl_comm_round_cost_for_config", "target": "users_ayberkkarataban_ssfl_with_psuedo_labeling_src_ssfl_comm_model_param_count", "relation": "calls", "context": "call", "confidence": "EXTRACTED", "source_file": "src/ssfl/comm.py", "source_location": "L168", "weight": 1.0}, {"source": "users_ayberkkarataban_ssfl_with_psuedo_labeling_src_ssfl_comm_round_cost_for_config", "target": "users_ayberkkarataban_ssfl_with_psuedo_labeling_src_ssfl_comm_round_cost", "relation": "calls", "context": "call", "confidence": "EXTRACTED", "source_file": "src/ssfl/comm.py", "source_location": "L169", "weight": 1.0}, {"source": "users_ayberkkarataban_ssfl_with_psuedo_labeling_src_ssfl_comm_cost_at_accuracy", "target": "users_ayberkkarataban_ssfl_with_psuedo_labeling_src_ssfl_comm_costat", "relation": "calls", "context": "call", "confidence": "EXTRACTED", "source_file": "src/ssfl/comm.py", "source_location": "L238", "weight": 1.0}, {"source": "users_ayberkkarataban_ssfl_with_psuedo_labeling_src_ssfl_comm_cost_at_top_acc", "target": "users_ayberkkarataban_ssfl_with_psuedo_labeling_src_ssfl_comm_costat", "relation": "calls", "context": "call", "confidence": "EXTRACTED", "source_file": "src/ssfl/comm.py", "source_location": "L253", "weight": 1.0}, {"source": "users_ayberkkarataban_ssfl_with_psuedo_labeling_src_ssfl_comm_cost_at_top_acc", "target": "users_ayberkkarataban_ssfl_with_psuedo_labeling_src_ssfl_comm_cost_at_accuracy", "relation": "calls", "context": "call", "confidence": "EXTRACTED", "source_file": "src/ssfl/comm.py", "source_location": "L255", "weight": 1.0}, {"source": "users_ayberkkarataban_ssfl_with_psuedo_labeling_src_ssfl_comm_cost_at_targets", "target": "users_ayberkkarataban_ssfl_with_psuedo_labeling_src_ssfl_comm_cost_at_accuracy", "relation": "calls", "context": "call", "confidence": "EXTRACTED", "source_file": "src/ssfl/comm.py", "source_location": "L266", "weight": 1.0}, {"source": "users_ayberkkarataban_ssfl_with_psuedo_labeling_src_ssfl_comm_cost_at_targets", "target": "users_ayberkkarataban_ssfl_with_psuedo_labeling_src_ssfl_comm_cost_at_top_acc", "relation": "calls", "context": "call", "confidence": "EXTRACTED", "source_file": "src/ssfl/comm.py", "source_location": "L271", "weight": 1.0}, {"source": "users_ayberkkarataban_ssfl_with_psuedo_labeling_src_ssfl_comm_run_comm_summary", "target": "path", "relation": "calls", "context": "call", "confidence": "EXTRACTED", "source_file": "src/ssfl/comm.py", "source_location": "L295", "weight": 1.0}, {"source": "users_ayberkkarataban_ssfl_with_psuedo_labeling_src_ssfl_comm_run_comm_summary", "target": "users_ayberkkarataban_ssfl_with_psuedo_labeling_src_ssfl_comm_scenario_num_clients", "relation": "calls", "context": "call", "confidence": "EXTRACTED", "source_file": "src/ssfl/comm.py", "source_location": "L305", "weight": 1.0}, {"source": "users_ayberkkarataban_ssfl_with_psuedo_labeling_src_ssfl_comm_run_comm_summary", "target": "users_ayberkkarataban_ssfl_with_psuedo_labeling_src_ssfl_comm_model_param_count", "relation": "calls", "context": "call", "confidence": "EXTRACTED", "source_file": "src/ssfl/comm.py", "source_location": "L307", "weight": 1.0}, {"source": "users_ayberkkarataban_ssfl_with_psuedo_labeling_src_ssfl_comm_run_comm_summary", "target": "users_ayberkkarataban_ssfl_with_psuedo_labeling_src_ssfl_comm_round_cost", "relation": "calls", "context": "call", "confidence": "EXTRACTED", "source_file": "src/ssfl/comm.py", "source_location": "L309", "weight": 1.0}, {"source": "users_ayberkkarataban_ssfl_with_psuedo_labeling_src_ssfl_comm_run_comm_summary", "target": "users_ayberkkarataban_ssfl_with_psuedo_labeling_src_ssfl_comm_open_set_cost_bytes", "relation": "calls", "context": "call", "confidence": "EXTRACTED", "source_file": "src/ssfl/comm.py", "source_location": "L325", "weight": 1.0}, {"source": "users_ayberkkarataban_ssfl_with_psuedo_labeling_src_ssfl_comm_run_comm_summary", "target": "users_ayberkkarataban_ssfl_with_psuedo_labeling_src_ssfl_comm_cumulative_mb_curve", "relation": "calls", "context": "call", "confidence": "EXTRACTED", "source_file": "src/ssfl/comm.py", "source_location": "L327", "weight": 1.0}, {"source": "users_ayberkkarataban_ssfl_with_psuedo_labeling_src_ssfl_comm_run_comm_summary", "target": "users_ayberkkarataban_ssfl_with_psuedo_labeling_src_ssfl_comm_cost_at_targets", "relation": "calls", "context": "call", "confidence": "EXTRACTED", "source_file": "src/ssfl/comm.py", "source_location": "L329", "weight": 1.0}, {"source": "users_ayberkkarataban_ssfl_with_psuedo_labeling_src_ssfl_comm_rationale_1", "target": "users_ayberkkarataban_ssfl_with_psuedo_labeling_src_ssfl_comm_py", "relation": "rationale_for", "confidence": "EXTRACTED", "source_file": "src/ssfl/comm.py", "source_location": "L1", "weight": 1.0}, {"source": "users_ayberkkarataban_ssfl_with_psuedo_labeling_src_ssfl_comm_rationale_66", "target": "users_ayberkkarataban_ssfl_with_psuedo_labeling_src_ssfl_comm_scenario_num_clients", "relation": "rationale_for", "confidence": "EXTRACTED", "source_file": "src/ssfl/comm.py", "source_location": "L66", "weight": 1.0}, {"source": "users_ayberkkarataban_ssfl_with_psuedo_labeling_src_ssfl_comm_rationale_77", "target": "users_ayberkkarataban_ssfl_with_psuedo_labeling_src_ssfl_comm_model_param_count", "relation": "rationale_for", "confidence": "EXTRACTED", "source_file": "src/ssfl/comm.py", "source_location": "L77", "weight": 1.0}, {"source": "users_ayberkkarataban_ssfl_with_psuedo_labeling_src_ssfl_comm_rationale_90", "target": "users_ayberkkarataban_ssfl_with_psuedo_labeling_src_ssfl_comm_roundcost", "relation": "rationale_for", "confidence": "EXTRACTED", "source_file": "src/ssfl/comm.py", "source_location": "L90", "weight": 1.0}, {"source": "users_ayberkkarataban_ssfl_with_psuedo_labeling_src_ssfl_comm_rationale_100", "target": "users_ayberkkarataban_ssfl_with_psuedo_labeling_src_ssfl_comm_roundcost_upload_bytes", "relation": "rationale_for", "confidence": "EXTRACTED", "source_file": "src/ssfl/comm.py", "source_location": "L100", "weight": 1.0}, {"source": "users_ayberkkarataban_ssfl_with_psuedo_labeling_src_ssfl_comm_rationale_105", "target": "users_ayberkkarataban_ssfl_with_psuedo_labeling_src_ssfl_comm_roundcost_download_bytes", "relation": "rationale_for", "confidence": "EXTRACTED", "source_file": "src/ssfl/comm.py", "source_location": "L105", "weight": 1.0}, {"source": "users_ayberkkarataban_ssfl_with_psuedo_labeling_src_ssfl_comm_rationale_126", "target": "users_ayberkkarataban_ssfl_with_psuedo_labeling_src_ssfl_comm_round_cost", "relation": "rationale_for", "confidence": "EXTRACTED", "source_file": "src/ssfl/comm.py", "source_location": "L126", "weight": 1.0}, {"source": "users_ayberkkarataban_ssfl_with_psuedo_labeling_src_ssfl_comm_rationale_160", "target": "users_ayberkkarataban_ssfl_with_psuedo_labeling_src_ssfl_comm_round_cost_for_config", "relation": "rationale_for", "confidence": "EXTRACTED", "source_file": "src/ssfl/comm.py", "source_location": "L160", "weight": 1.0}, {"source": "users_ayberkkarataban_ssfl_with_psuedo_labeling_src_ssfl_comm_rationale_186", "target": "users_ayberkkarataban_ssfl_with_psuedo_labeling_src_ssfl_comm_open_set_cost_bytes", "relation": "rationale_for", "confidence": "EXTRACTED", "source_file": "src/ssfl/comm.py", "source_location": "L186", "weight": 1.0}, {"source": "users_ayberkkarataban_ssfl_with_psuedo_labeling_src_ssfl_comm_rationale_199", "target": "users_ayberkkarataban_ssfl_with_psuedo_labeling_src_ssfl_comm_cumulative_mb_curve", "relation": "rationale_for", "confidence": "EXTRACTED", "source_file": "src/ssfl/comm.py", "source_location": "L199", "weight": 1.0}, {"source": "users_ayberkkarataban_ssfl_with_psuedo_labeling_src_ssfl_comm_rationale_209", "target": "users_ayberkkarataban_ssfl_with_psuedo_labeling_src_ssfl_comm_costat", "relation": "rationale_for", "confidence": "EXTRACTED", "source_file": "src/ssfl/comm.py", "source_location": "L209", "weight": 1.0}, {"source": "users_ayberkkarataban_ssfl_with_psuedo_labeling_src_ssfl_comm_rationale_228", "target": "users_ayberkkarataban_ssfl_with_psuedo_labeling_src_ssfl_comm_cost_at_accuracy", "relation": "rationale_for", "confidence": "EXTRACTED", "source_file": "src/ssfl/comm.py", "source_location": "L228", "weight": 1.0}, {"source": "users_ayberkkarataban_ssfl_with_psuedo_labeling_src_ssfl_comm_rationale_251", "target": "users_ayberkkarataban_ssfl_with_psuedo_labeling_src_ssfl_comm_cost_at_top_acc", "relation": "rationale_for", "confidence": "EXTRACTED", "source_file": "src/ssfl/comm.py", "source_location": "L251", "weight": 1.0}, {"source": "users_ayberkkarataban_ssfl_with_psuedo_labeling_src_ssfl_comm_rationale_264", "target": "users_ayberkkarataban_ssfl_with_psuedo_labeling_src_ssfl_comm_cost_at_targets", "relation": "rationale_for", "confidence": "EXTRACTED", "source_file": "src/ssfl/comm.py", "source_location": "L264", "weight": 1.0}, {"source": "users_ayberkkarataban_ssfl_with_psuedo_labeling_src_ssfl_comm_rationale_283", "target": "users_ayberkkarataban_ssfl_with_psuedo_labeling_src_ssfl_comm_run_comm_summary", "relation": "rationale_for", "confidence": "EXTRACTED", "source_file": "src/ssfl/comm.py", "source_location": "L283", "weight": 1.0}], "raw_calls": [{"caller_nid": "users_ayberkkarataban_ssfl_with_psuedo_labeling_src_ssfl_comm_scenario_num_clients", "callee": "ValueError", "is_member_call": false, "source_file": "/Users/ayberkkarataban/SSFL with Psuedo Labeling/src/ssfl/comm.py", "source_location": "L70", "receiver": null}, {"caller_nid": "users_ayberkkarataban_ssfl_with_psuedo_labeling_src_ssfl_comm_scenario_num_clients", "callee": "join", "is_member_call": true, "source_file": "/Users/ayberkkarataban/SSFL with Psuedo Labeling/src/ssfl/comm.py", "source_location": "L72", "receiver": null}, {"caller_nid": "users_ayberkkarataban_ssfl_with_psuedo_labeling_src_ssfl_comm_scenario_num_clients", "callee": "str", "is_member_call": false, "indirect": true, "context": "argument", "source_file": "/Users/ayberkkarataban/SSFL with Psuedo Labeling/src/ssfl/comm.py", "source_location": "L72"}, {"caller_nid": "users_ayberkkarataban_ssfl_with_psuedo_labeling_src_ssfl_comm_scenario_num_clients", "callee": "SCENARIO_NUM_CLIENTS", "is_member_call": false, "indirect": true, "context": "argument", "source_file": "/Users/ayberkkarataban/SSFL with Psuedo Labeling/src/ssfl/comm.py", "source_location": "L72"}, {"caller_nid": "users_ayberkkarataban_ssfl_with_psuedo_labeling_src_ssfl_comm_model_param_count", "callee": "numel", "is_member_call": true, "source_file": "/Users/ayberkkarataban/SSFL with Psuedo Labeling/src/ssfl/comm.py", "source_location": "L85", "receiver": "p"}, {"caller_nid": "users_ayberkkarataban_ssfl_with_psuedo_labeling_src_ssfl_comm_model_param_count", "callee": "parameters", "is_member_call": true, "source_file": "/Users/ayberkkarataban/SSFL with Psuedo Labeling/src/ssfl/comm.py", "source_location": "L85", "receiver": null}, {"caller_nid": "users_ayberkkarataban_ssfl_with_psuedo_labeling_src_ssfl_comm_model_param_count", "callee": "build_model", "is_member_call": false, "source_file": "/Users/ayberkkarataban/SSFL with Psuedo Labeling/src/ssfl/comm.py", "source_location": "L85", "receiver": null}, {"caller_nid": "users_ayberkkarataban_ssfl_with_psuedo_labeling_src_ssfl_comm_round_cost", "callee": "int", "is_member_call": false, "indirect": true, "context": "argument", "source_file": "/Users/ayberkkarataban/SSFL with Psuedo Labeling/src/ssfl/comm.py", "source_location": "L131"}, {"caller_nid": "users_ayberkkarataban_ssfl_with_psuedo_labeling_src_ssfl_comm_round_cost", "callee": "ValueError", "is_member_call": false, "source_file": "/Users/ayberkkarataban/SSFL with Psuedo Labeling/src/ssfl/comm.py", "source_location": "L132", "receiver": null}, {"caller_nid": "users_ayberkkarataban_ssfl_with_psuedo_labeling_src_ssfl_comm_round_cost", "callee": "items", "is_member_call": true, "source_file": "/Users/ayberkkarataban/SSFL with Psuedo Labeling/src/ssfl/comm.py", "source_location": "L138", "receiver": "dims"}, {"caller_nid": "users_ayberkkarataban_ssfl_with_psuedo_labeling_src_ssfl_comm_round_cost", "callee": "payload_nbytes", "is_member_call": false, "source_file": "/Users/ayberkkarataban/SSFL with Psuedo Labeling/src/ssfl/comm.py", "source_location": "L143", "receiver": null}, {"caller_nid": "users_ayberkkarataban_ssfl_with_psuedo_labeling_src_ssfl_comm_round_cost", "callee": "payload_nbytes", "is_member_call": false, "source_file": "/Users/ayberkkarataban/SSFL with Psuedo Labeling/src/ssfl/comm.py", "source_location": "L146", "receiver": null}, {"caller_nid": "users_ayberkkarataban_ssfl_with_psuedo_labeling_src_ssfl_comm_open_set_cost_bytes", "callee": "ValueError", "is_member_call": false, "source_file": "/Users/ayberkkarataban/SSFL with Psuedo Labeling/src/ssfl/comm.py", "source_location": "L192", "receiver": null}, {"caller_nid": "users_ayberkkarataban_ssfl_with_psuedo_labeling_src_ssfl_comm_cumulative_mb_curve", "callee": "arange", "is_member_call": true, "source_file": "/Users/ayberkkarataban/SSFL with Psuedo Labeling/src/ssfl/comm.py", "source_location": "L204", "receiver": "np"}, {"caller_nid": "users_ayberkkarataban_ssfl_with_psuedo_labeling_src_ssfl_comm_run_comm_summary", "callee": "exists", "is_member_call": true, "source_file": "/Users/ayberkkarataban/SSFL with Psuedo Labeling/src/ssfl/comm.py", "source_location": "L297", "receiver": "config_path"}, {"caller_nid": "users_ayberkkarataban_ssfl_with_psuedo_labeling_src_ssfl_comm_run_comm_summary", "callee": "FileNotFoundError", "is_member_call": false, "source_file": "/Users/ayberkkarataban/SSFL with Psuedo Labeling/src/ssfl/comm.py", "source_location": "L298", "receiver": null}, {"caller_nid": "users_ayberkkarataban_ssfl_with_psuedo_labeling_src_ssfl_comm_run_comm_summary", "callee": "loads", "is_member_call": true, "source_file": "/Users/ayberkkarataban/SSFL with Psuedo Labeling/src/ssfl/comm.py", "source_location": "L301", "receiver": "json"}, {"caller_nid": "users_ayberkkarataban_ssfl_with_psuedo_labeling_src_ssfl_comm_run_comm_summary", "callee": "read_text", "is_member_call": true, "source_file": "/Users/ayberkkarataban/SSFL with Psuedo Labeling/src/ssfl/comm.py", "source_location": "L301", "receiver": "config_path"}, {"caller_nid": "users_ayberkkarataban_ssfl_with_psuedo_labeling_src_ssfl_comm_run_comm_summary", "callee": "get", "is_member_call": true, "source_file": "/Users/ayberkkarataban/SSFL with Psuedo Labeling/src/ssfl/comm.py", "source_location": "L304", "receiver": "raw"}, {"caller_nid": "users_ayberkkarataban_ssfl_with_psuedo_labeling_src_ssfl_comm_run_comm_summary", "callee": "read_rounds", "is_member_call": false, "source_file": "/Users/ayberkkarataban/SSFL with Psuedo Labeling/src/ssfl/comm.py", "source_location": "L317", "receiver": null}, {"caller_nid": "users_ayberkkarataban_ssfl_with_psuedo_labeling_src_ssfl_comm_run_comm_summary", "callee": "update", "is_member_call": true, "source_file": "/Users/ayberkkarataban/SSFL with Psuedo Labeling/src/ssfl/comm.py", "source_location": "L329", "receiver": "summary"}]}